pynmr/__init__.py
pynmr-0.27.dist-info/LICENSE
pynmr-0.27.dist-info/METADATA
pynmr-0.27.dist-info/WHEEL
pynmr-0.27.dist-info/top_level.txt
pynmr-0.27.dist-info/RECORD
