Metadata-Version: 2.1
Name: pynmr
Version: 0.27
Summary: Parse and Process NMR data.
Home-page: http://github.com/bennomeier/pyNMR
Author: Benno Meier
Author-email: meier.benno@gmail.com
License: MIT
Keywords: pynmr NMR TopSpin RS2D NTNMR Magritek
Platform: UNKNOWN
Classifier: License :: OSI Approved :: MIT License
Classifier: Programming Language :: Python
Classifier: Topic :: Scientific/Engineering :: Physics
Requires-Dist: numpy
Requires-Dist: spindata
Requires-Dist: scipy
Requires-Dist: paramiko
Requires-Dist: pyqtgraph
Requires-Dist: PyQt5
Requires-Dist: BeautifulSoup4
